bcd.v
module bcd(clk, rst_syn,out,load,seg,Din); 
input clk,load;
input rst_syn;
input Din;
output[3:0] out;
reg [3:0] out;
output [7:0] seg;
reg [7:0] seg;

always@ (posedge clk)
begin
    if(!rst_syn)
        out=0;
    else if (load) 
        out <=Din; 
    else if(out ==9)
        out=0;
    else    
        out=out+1;
end
always @(out)
    begin
        case (out) 
            0 : seg = 8'b11000000;
            1 : seg = 8'b11111001;
            2 : seg = 8'b10100100;
            3 : seg = 8'b10110000;
            4 : seg = 8'b10011001;
            5 : seg = 8'b10010010;
            6 : seg = 8'b10000010;
            7 : seg = 8'b11111000;
            8 : seg = 8'b10000000;
            9 : seg = 8'b10010000;
            10: seg = 8'b10100000;
            11: seg = 8'b10100111;
            13: seg = 8'b10100001;
            14: seg = 8'b10000100;
            15: seg = 8'b11110001;
            default : seg = 8'b11111111; 
        endcase
    end
endmodule

bcd_tb.v
`timescale 1ns/1ps
module  bcd_tb;
reg clk;
reg rst_n;
reg Din;
reg load;
wire [3:0] out;
wire [7:0] seg; 
parameter  PERIOD=20 ;
parameter  real DUTY_CUCLE =0.5;
parameter  OFFSET =0;
initial begin
    #OFFSET;
    forever
        begin
        Din= 4'b0001;
        clk=1'b1;
        #(PERIOD-(PERIOD*DUTY_CUCLE))   clk=1'b0;
        #(PERIOD*DUTY_CUCLE);
        end
end

initial begin
    rst_n = 1'b0;
    #5 rst_n = 1'b1;
    #195 rst_n =1'b0;
    #5 rst_n = 1'b1;
    #55 $finish;
end
initial begin
    load= 1'b0;
    #200 load = 1'b1;
    #10 load = 1'b0;
    #500 $finish;
end
initial begin
    $dumpfile("bcd.vcd");
    $dumpvars(0, bcd_1);
end
bcd bcd_1(.clk(clk),
          .rst_syn(rst_n),
          .out(out),
          .Din(Din),
          .seg(seg),
          .load(load));
endmodule

bcd.vcd
$date
	Sat May 07 13:03:42 2022
$end
$version
	Icarus Verilog
$end
$timescale
	1ps
$end
$scope module bcd_tb $end
$scope module bcd_1 $end
$var wire 1 ! Din $end
$var wire 1 " clk $end
$var wire 1 # load $end
$var wire 1 $ rst_syn $end
$var reg 4 % out [3:0] $end
$var reg 8 & seg [7:0] $end
$upscope $end
$upscope $end
$enddefinitions $end
#0
$dumpvars
b11000000 &
b0 %
0$
0#
1"
1!
$end
#5000
1$
#10000
0"
#20000
b11111001 &
b1 %
1"
#30000
0"
#40000
b10100100 &
b10 %
1"
#50000
0"
#60000
b10110000 &
b11 %
1"
#70000
0"
#80000
b10011001 &
b100 %
1"
#90000
0"
#100000
b10010010 &
b101 %
1"
#110000
0"
#120000
b10000010 &
b110 %
1"
#130000
0"
#140000
b11111000 &
b111 %
1"
#150000
0"
#160000
b10000000 &
b1000 %
1"
#170000
0"
#180000
b10010000 &
b1001 %
1"
#190000
0"
#200000
b11000000 &
b0 %
1"
0$
1#
#205000
1$
#210000
0"
0#
#220000
b11111001 &
b1 %
1"
#230000
0"
#240000
b10100100 &
b10 %
1"
#250000
0"
#260000
b10110000 &
b11 %
1"
